MANIFEST.in
setup.py
src/tiberium_soul/__init__.py
src/tiberium_soul/main.py
src/tiberium_soul/proxy.py
src/tiberium_soul/run.py
src/tiberium_soul.egg-info/PKG-INFO
src/tiberium_soul.egg-info/SOURCES.txt
src/tiberium_soul.egg-info/dependency_links.txt
src/tiberium_soul.egg-info/entry_points.txt
src/tiberium_soul.egg-info/not-zip-safe
src/tiberium_soul.egg-info/requires.txt
src/tiberium_soul.egg-info/top_level.txt
src/tiberium_soul/cert/dummy.crt
src/tiberium_soul/cert/dummy.csr
src/tiberium_soul/cert/dummy.key
src/tiberium_soul/global/config.json
src/tiberium_soul/hooks/post-receive
src/tiberium_soul/repos/readme.md
src/tiberium_soul/static/css/layout.css
src/tiberium_soul/static/images/favicon.ico
src/tiberium_soul/static/images/logo-footer.png
src/tiberium_soul/static/js/main.js
src/tiberium_soul/suns/readme.md
src/tiberium_soul/templates/about.html.tpl
src/tiberium_soul/templates/app
src/tiberium_soul/templates/index.html.tpl
src/tiberium_soul/templates/partials
src/tiberium_soul/templates/app/delete.html.tpl
src/tiberium_soul/templates/app/edit.html.tpl
src/tiberium_soul/templates/app/help.html.tpl
src/tiberium_soul/templates/app/list.html.tpl
src/tiberium_soul/templates/app/new.html.tpl
src/tiberium_soul/templates/app/show.html.tpl
src/tiberium_soul/templates/partials/content_type.html.tpl
src/tiberium_soul/templates/partials/doctype.html.tpl
src/tiberium_soul/templates/partials/end_doctype.html.tpl
src/tiberium_soul/templates/partials/footer.html.tpl
src/tiberium_soul/templates/partials/includes.html.tpl
src/tiberium_soul/templates/partials/layout.html.tpl
src/tiberium_soul/templates/partials/layout_app.html.tpl
src/tiberium_soul/templates/partials/layout_simple.html.tpl
src/tiberium_soul/tmp/readme.md
src/tiberium_soul/util/__init__.py
src/tiberium_soul/util/logic.py
src/tiberium_soul/util/model.py
src/tiberium_soul/views/__init__.py
src/tiberium_soul/views/api/__init__.py
src/tiberium_soul/views/web/__init__.py
src/tiberium_soul/views/web/_app.py
src/tiberium_soul/views/web/base.py